lruttl/__init__.py
lruttl/lru.py
lru_ttl-0.0.7.dist-info/LICENSE.txt
lru_ttl-0.0.7.dist-info/METADATA
lru_ttl-0.0.7.dist-info/WHEEL
lru_ttl-0.0.7.dist-info/top_level.txt
lru_ttl-0.0.7.dist-info/RECORD
