Metadata-Version: 2.1
Name: lru-ttl
Version: 0.0.7
Summary: A least recently used (LRU) cache implementation with time to live (TTL)
Home-page: https://github.com/arnov/lru-ttl
Author: Arno Veenstra
Author-email: arnoveenstra@gmail.com
License: UNKNOWN
Platform: UNKNOWN
Classifier: Programming Language :: Python :: 3
Classifier: Programming Language :: Python :: 2
Classifier: Development Status :: 5 - Production/Stable
Classifier: Intended Audience :: Developers
Classifier: License :: OSI Approved :: MIT License
Classifier: Operating System :: OS Independent
Classifier: Topic :: Software Development :: Libraries :: Python Modules
